[
  {"word": "чёрный", "theme": "colors"},
  {"word": "дочь", "theme": "family"},
  {"word": "брюссельская капуста", "theme": "food"},
  {"word": "шпроты", "theme": "food"},
  {"word": "шампанское", "theme": "food"},
  {"word": "приехать", "theme": "travel"},
  {"word": "больница", "theme": "health"},
  {"word": "тело", "theme": "health"},
  {"word": "короткий", "theme": "general"},
  {"word": "год", "theme": "time"},
  {"word": "утка", "theme": "food"},
  {"word": "голова", "theme": "health"},
  {"word": "сынок", "theme": "family"},
  {"word": "заснуть", "theme": "general"},
  {"word": "ремень", "theme": "clothing"},
  {"word": "бобовые", "theme": "food"},
  {"word": "свояк", "theme": "family"},
  {"word": "виноград", "theme": "food"},
  {"word": "пояс", "theme": "clothing"},
  {"word": "бейсболка", "theme": "clothing"},
  {"word": "бублик", "theme": "food"},
  {"word": "удаваться", "theme": "general"},
  {"word": "бабочка", "theme": "nature"},
  {"word": "бюстгальтер", "theme": "clothing"},
  {"word": "пассажирка", "theme": "travel"},
  {"word": "грудь", "theme": "health"},
  {"word": "обувь", "theme": "clothing"},
  {"word": "халва", "theme": "food"},
  {"word": "пепси", "theme": "food"},
  {"word": "огурец", "theme": "food"},
  {"word": "помогать", "theme": "general"},
  {"word": "шкурка", "theme": "food"},
  {"word": "должен", "theme": "general"},
  {"word": "семья", "theme": "family"},
  {"word": "овощи", "theme": "food"},
  {"word": "еда", "theme": "food"},
  {"word": "сырник", "theme": "food"},
  {"word": "искупаться", "theme": "general"},
  {"word": "привет", "theme": "communication"},
  {"word": "горячий", "theme": "general"},
  {"word": "правнучка", "theme": "family"},
  {"word": "отбивная", "theme": "food"},
  {"word": "кафе", "theme": "food"},
  {"word": "розовый", "theme": "colors"},
  {"word": "гнать", "theme": "general"},
  {"word": "капучино", "theme": "food"},
  {"word": "сарделька", "theme": "food"},
  {"word": "серьга", "theme": "clothing"},
  {"word": "американо", "theme": "food"},
  {"word": "сделать", "theme": "general"},
  {"word": "борода", "theme": "health"},
  {"word": "плавки", "theme": "clothing"},
  {"word": "позавтракать", "theme": "food"},
  {"word": "пуп", "theme": "health"},
  {"word": "интересный", "theme": "general"},
  {"word": "клиент", "theme": "shopping"},
  {"word": "кожица", "theme": "food"},
  {"word": "горячий шоколад", "theme": "food"},
  {"word": "ресницы", "theme": "health"},
  {"word": "шпинат", "theme": "food"},
  {"word": "сахарный", "theme": "food"},
  {"word": "кефир", "theme": "food"},
  {"word": "косточка", "theme": "food"},
  {"word": "сахар", "theme": "food"},
  {"word": "судак", "theme": "food"},
  {"word": "человек", "theme": "general"},
  {"word": "розовое вино", "theme": "food"},
  {"word": "кока-кола", "theme": "food"},
  {"word": "томат", "theme": "food"},
  {"word": "рукавицы", "theme": "clothing"},
  {"word": "шляпа", "theme": "clothing"},
  {"word": "клиентка", "theme": "shopping"},
  {"word": "плыть", "theme": "sports"},
  {"word": "палтус", "theme": "food"},
  {"word": "предплечье", "theme": "health"},
  {"word": "полететь", "theme": "travel"},
  {"word": "зелёный горошек", "theme": "food"},
  {"word": "правнук", "theme": "family"},
  {"word": "желудок", "theme": "health"},
  {"word": "сом", "theme": "food"},
  {"word": "лёгкие", "theme": "health"},
  {"word": "оно", "theme": "general"},
  {"word": "помело", "theme": "food"},
  {"word": "кровать", "theme": "home"},
  {"word": "алыча", "theme": "food"},
  {"word": "талия", "theme": "health"},
  {"word": "блуза", "theme": "clothing"},
  {"word": "муж", "theme": "family"},
  {"word": "грибы", "theme": "food"},
  {"word": "горожанин", "theme": "general"},
  {"word": "айва", "theme": "food"},
  {"word": "ликёр", "theme": "food"},
  {"word": "курица", "theme": "food"},
  {"word": "колготки", "theme": "clothing"},
  {"word": "объяснять", "theme": "communication"},
  {"word": "сумка", "theme": "clothing"},
  {"word": "до свидания", "theme": "communication"},
  {"word": "малина", "theme": "food"},
  {"word": "пуловер", "theme": "clothing"},
  {"word": "вдова", "theme": "family"},
  {"word": "доченька", "theme": "family"},
  {"word": "кета", "theme": "food"},
  {"word": "белок", "theme": "food"},
  {"word": "мидия", "theme": "food"},
  {"word": "эскалоп", "theme": "food"},
  {"word": "серьги", "theme": "clothing"},
  {"word": "пока", "theme": "communication"},
  {"word": "берет", "theme": "clothing"},
  {"word": "рыба", "theme": "food"},
  {"word": "горло", "theme": "health"},
  {"word": "портфель", "theme": "education"},
  {"word": "летать", "theme": "travel"},
  {"word": "манго", "theme": "food"},
  {"word": "нижнее бельё", "theme": "clothing"},
  {"word": "апельсин", "theme": "food"},
  {"word": "месяц", "theme": "time"},
  {"word": "изюм", "theme": "food"},
  {"word": "поехать", "theme": "travel"},
  {"word": "запеканка", "theme": "food"},
  {"word": "чечевица", "theme": "food"},
  {"word": "маракуйя", "theme": "food"},
  {"word": "ладонь", "theme": "health"},
  {"word": "шницель", "theme": "food"},
  {"word": "учиться", "theme": "education"},
  {"word": "гуава", "theme": "food"},
  {"word": "знать", "theme": "general"},
  {"word": "искать", "theme": "general"},
  {"word": "соя", "theme": "food"},
  {"word": "светлое пиво", "theme": "food"},
  {"word": "почему", "theme": "general"},
  {"word": "плохо", "theme": "general"},
  {"word": "ребёнок", "theme": "family"},
  {"word": "помидор", "theme": "food"},
  {"word": "коричневый", "theme": "colors"},
  {"word": "решать", "theme": "general"},
  {"word": "артерия", "theme": "health"},
  {"word": "белый гриб", "theme": "food"},
  {"word": "брокколи", "theme": "food"},
  {"word": "антрекот", "theme": "food"},
  {"word": "желток", "theme": "food"},
  {"word": "топ", "theme": "clothing"},
  {"word": "питьё", "theme": "food"},
  {"word": "поганка", "theme": "food"},
  {"word": "шашлык", "theme": "food"},
  {"word": "сидеть", "theme": "general"},
  {"word": "вечер", "theme": "time"},
  {"word": "щека", "theme": "health"},
  {"word": "важный", "theme": "general"},
  {"word": "незнакомец", "theme": "general"},
  {"word": "дедушка", "theme": "family"},
  {"word": "пальцы", "theme": "health"},
  {"word": "показаться", "theme": "general"},
  {"word": "ноги", "theme": "health"},
  {"word": "кровь", "theme": "health"},
  {"word": "эскимо", "theme": "food"},
  {"word": "латук", "theme": "food"},
  {"word": "поработать", "theme": "work"},
  {"word": "айсберг", "theme": "food"},
  {"word": "волосы", "theme": "health"},
  {"word": "предлагать", "theme": "general"},
  {"word": "мозги", "theme": "health"},
  {"word": "люди", "theme": "general"},
  {"word": "где", "theme": "general"},
  {"word": "жених", "theme": "family"},
  {"word": "чёрный шоколад", "theme": "food"},
  {"word": "бегать", "theme": "sports"},
  {"word": "подберёзовик", "theme": "food"},
  {"word": "таскать", "theme": "general"},
  {"word": "смузи", "theme": "food"},
  {"word": "приготовить", "theme": "food"},
  {"word": "гоголь-моголь", "theme": "food"},
  {"word": "незнакомка", "theme": "general"},
  {"word": "ночная рубашка", "theme": "clothing"},
  {"word": "знакомая", "theme": "general"},
  {"word": "сказать", "theme": "communication"},
  {"word": "ногти", "theme": "health"},
  {"word": "решить", "theme": "general"},
  {"word": "порей", "theme": "food"},
  {"word": "везти", "theme": "travel"},
  {"word": "минералка", "theme": "food"},
  {"word": "музей", "theme": "culture"},
  {"word": "пальто", "theme": "clothing"},
  {"word": "тыква", "theme": "food"},
  {"word": "сок", "theme": "food"},
  {"word": "причесаться", "theme": "general"},
  {"word": "футболка", "theme": "clothing"},
  {"word": "бабушка", "theme": "family"},
  {"word": "пиджак", "theme": "clothing"},
  {"word": "нести", "theme": "general"},
  {"word": "внук", "theme": "family"},
  {"word": "родственница", "theme": "family"},
  {"word": "двоюродный брат", "theme": "family"},
  {"word": "приятельница", "theme": "general"},
  {"word": "садиться", "theme": "general"},
  {"word": "дыня", "theme": "food"},
  {"word": "рисовая каша", "theme": "food"},
  {"word": "пить", "theme": "food"},
  {"word": "брынза", "theme": "food"},
  {"word": "карп", "theme": "food"},
  {"word": "уходить", "theme": "general"},
  {"word": "пралине", "theme": "food"},
  {"word": "яичница", "theme": "food"},
  {"word": "ступня", "theme": "health"},
  {"word": "гонять", "theme": "general"},
  {"word": "уметь", "theme": "general"},
  {"word": "дед", "theme": "family"},
  {"word": "начинать", "theme": "general"},
  {"word": "девочка", "theme": "family"},
  {"word": "просыпаться", "theme": "general"},
  {"word": "рамбутан", "theme": "food"},
  {"word": "прийти", "theme": "general"},
  {"word": "продавец", "theme": "shopping"},
  {"word": "морепродукты", "theme": "food"},
  {"word": "она", "theme": "general"},
  {"word": "стоять", "theme": "general"},
  {"word": "побриться", "theme": "general"},
  {"word": "мозг", "theme": "health"},
  {"word": "шоколад", "theme": "food"},
  {"word": "они", "theme": "general"},
  {"word": "ресница", "theme": "health"},
  {"word": "грецкий орех", "theme": "food"},
  {"word": "брага", "theme": "food"},
  {"word": "лицо", "theme": "health"},
  {"word": "кешью", "theme": "food"},
  {"word": "чёрный чай", "theme": "food"},
  {"word": "волос", "theme": "health"},
  {"word": "тот", "theme": "general"},
  {"word": "поджарить", "theme": "food"},
  {"word": "горох", "theme": "food"},
  {"word": "чили", "theme": "food"},
  {"word": "фанта", "theme": "food"},
  {"word": "ложиться", "theme": "general"},
  {"word": "двоюродная сестра", "theme": "family"},
  {"word": "кинза", "theme": "food"},
  {"word": "кукуруза", "theme": "food"},
  {"word": "турист", "theme": "travel"},
  {"word": "клык", "theme": "health"},
  {"word": "зять", "theme": "family"},
  {"word": "накраситься", "theme": "general"},
  {"word": "щавель", "theme": "food"},
  {"word": "постоять", "theme": "general"},
  {"word": "осьминог", "theme": "food"},
  {"word": "один", "theme": "numbers"},
  {"word": "бижутерия", "theme": "clothing"},
  {"word": "жвачка", "theme": "food"},
  {"word": "сметана", "theme": "food"},
  {"word": "сапоги", "theme": "clothing"},
  {"word": "жарить", "theme": "food"},
  {"word": "чёрная смородина", "theme": "food"},
  {"word": "повести", "theme": "general"},
  {"word": "крестьянин", "theme": "general"},
  {"word": "холодный", "theme": "general"},
  {"word": "джин", "theme": "food"},
  {"word": "красный", "theme": "colors"},
  {"word": "большой палец", "theme": "health"},
  {"word": "доброе утро", "theme": "communication"},
  {"word": "кальмары", "theme": "food"},
  {"word": "вена", "theme": "health"},
  {"word": "лёгкий", "theme": "general"},
  {"word": "ползти", "theme": "general"},
  {"word": "лифчик", "theme": "clothing"},
  {"word": "завтракать", "theme": "food"},
  {"word": "стать", "theme": "general"},
  {"word": "умыться", "theme": "general"},
  {"word": "кость", "theme": "health"},
  {"word": "редис", "theme": "food"},
  {"word": "иностранка", "theme": "general"},
  {"word": "платок", "theme": "clothing"},
  {"word": "супруга", "theme": "family"},
  {"word": "лисички", "theme": "food"},
  {"word": "вода", "theme": "food"},
  {"word": "сушка", "theme": "food"},
  {"word": "молодожёны", "theme": "family"},
  {"word": "индейка", "theme": "food"},
  {"word": "продолжать", "theme": "general"},
  {"word": "ряженка", "theme": "food"},
  {"word": "станция", "theme": "travel"},
  {"word": "соседка", "theme": "general"},
  {"word": "самогон", "theme": "food"},
  {"word": "кресс-салат", "theme": "food"},
  {"word": "фарш", "theme": "food"},
  {"word": "перец", "theme": "food"},
  {"word": "щука", "theme": "food"},
  {"word": "ждать", "theme": "general"},
  {"word": "блины", "theme": "food"},
  {"word": "продукты", "theme": "food"},
  {"word": "резинка", "theme": "general"},
  {"word": "бок", "theme": "health"},
  {"word": "батон", "theme": "food"},
  {"word": "живот", "theme": "health"},
  {"word": "молочный коктейль", "theme": "food"},
  {"word": "черноплодная рябина", "theme": "food"},
  {"word": "куртка", "theme": "clothing"},
  {"word": "вафли", "theme": "food"},
  {"word": "щёки", "theme": "health"},
  {"word": "колено", "theme": "health"},
  {"word": "зубы", "theme": "health"},
  {"word": "костюм", "theme": "clothing"},
  {"word": "хорошо", "theme": "general"},
  {"word": "раздеться", "theme": "general"},
  {"word": "лимон", "theme": "food"},
  {"word": "солянка", "theme": "food"},
  {"word": "выбирать", "theme": "general"},
  {"word": "что", "theme": "general"},
  {"word": "кожура", "theme": "food"},
  {"word": "блин", "theme": "food"},
  {"word": "панама", "theme": "clothing"},
  {"word": "дети", "theme": "family"},
  {"word": "два", "theme": "numbers"},
  {"word": "сыр", "theme": "food"},
  {"word": "устрица", "theme": "food"},
  {"word": "вино", "theme": "food"},
  {"word": "средний палец", "theme": "health"},
  {"word": "сморчок", "theme": "food"},
  {"word": "борщ", "theme": "food"},
  {"word": "покупательница", "theme": "shopping"},
  {"word": "овощ", "theme": "food"},
  {"word": "рассказывать", "theme": "communication"},
  {"word": "хлеб", "theme": "food"},
  {"word": "гусь", "theme": "food"},
  {"word": "тунец", "theme": "food"},
  {"word": "плечо", "theme": "health"},
  {"word": "попытаться", "theme": "general"},
  {"word": "леденец", "theme": "food"},
  {"word": "глаза", "theme": "health"},
  {"word": "танжерин", "theme": "food"},
  {"word": "суметь", "theme": "general"},
  {"word": "я", "theme": "general"},
  {"word": "котлета", "theme": "food"},
  {"word": "стол", "theme": "home"},
  {"word": "репчатый лук", "theme": "food"},
  {"word": "ирис", "theme": "food"},
  {"word": "шарф", "theme": "clothing"},
  {"word": "сумочка", "theme": "clothing"},
  {"word": "банан", "theme": "food"},
  {"word": "проснуться", "theme": "general"},
  {"word": "кебаб", "theme": "food"},
  {"word": "веко", "theme": "health"},
  {"word": "булка", "theme": "food"},
  {"word": "шорты", "theme": "clothing"},
  {"word": "двойняшки", "theme": "family"},
  {"word": "петля", "theme": "general"},
  {"word": "желе", "theme": "food"},
  {"word": "вдовец", "theme": "family"},
  {"word": "виноградина", "theme": "food"},
  {"word": "мидии", "theme": "food"},
  {"word": "серый", "theme": "colors"},
  {"word": "выпить", "theme": "food"},
  {"word": "белая смородина", "theme": "food"},
  {"word": "оладьи", "theme": "food"},
  {"word": "терять", "theme": "general"},
  {"word": "шалот", "theme": "food"},
  {"word": "тёща", "theme": "family"},
  {"word": "дочка", "theme": "family"},
  {"word": "глинтвейн", "theme": "food"},
  {"word": "черника", "theme": "food"},
  {"word": "повидло", "theme": "food"},
  {"word": "пойти", "theme": "general"},
  {"word": "сирота", "theme": "family"},
  {"word": "квас", "theme": "food"},
  {"word": "жаркое", "theme": "food"},
  {"word": "старый", "theme": "general"},
  {"word": "капучино", "theme": "food"},
  {"word": "чулки", "theme": "clothing"},
  {"word": "носить", "theme": "general"},
  {"word": "клементин", "theme": "food"},
  {"word": "советовать", "theme": "communication"},
  {"word": "жена", "theme": "family"},
  {"word": "сырники", "theme": "food"},
  {"word": "старик", "theme": "general"},
  {"word": "торт", "theme": "food"},
  {"word": "перчатки", "theme": "clothing"},
  {"word": "взять", "theme": "general"},
  {"word": "спрашивать", "theme": "communication"},
  {"word": "мочь", "theme": "general"},
  {"word": "минеральная вода", "theme": "food"},
  {"word": "приятель", "theme": "general"},
  {"word": "бриться", "theme": "general"},
  {"word": "колени", "theme": "health"},
  {"word": "мухомор", "theme": "food"},
  {"word": "лепёшка", "theme": "food"},
  {"word": "грейпфрут", "theme": "food"},
  {"word": "мамочка", "theme": "family"},
  {"word": "облепиха", "theme": "food"},
  {"word": "растворимый кофе", "theme": "food"},
  {"word": "кончить", "theme": "general"},
  {"word": "сегодня", "theme": "time"},
  {"word": "гранат", "theme": "food"},
  {"word": "болгарский перец", "theme": "food"},
  {"word": "нугат", "theme": "food"},
  {"word": "бедро", "theme": "health"},
  {"word": "смочь", "theme": "general"},
  {"word": "стул", "theme": "home"},
  {"word": "каблук", "theme": "clothing"},
  {"word": "плавать", "theme": "sports"},
  {"word": "цитрусовые", "theme": "food"},
  {"word": "маслёнок", "theme": "food"},
  {"word": "ночь", "theme": "time"},
  {"word": "окно", "theme": "home"},
  {"word": "печень", "theme": "health"},
  {"word": "икра", "theme": "food"},
  {"word": "гроздь", "theme": "food"},
  {"word": "добрый вечер", "theme": "communication"},
  {"word": "руккола", "theme": "food"},
  {"word": "лещина", "theme": "food"},
  {"word": "лосось", "theme": "food"},
  {"word": "пирожок", "theme": "food"},
  {"word": "накидка", "theme": "clothing"},
  {"word": "текила", "theme": "food"},
  {"word": "кто", "theme": "general"},
  {"word": "кончать", "theme": "general"},
  {"word": "устрицы", "theme": "food"},
  {"word": "завтра", "theme": "time"}
]
